abstract_image_viewer/__init__.py
abstract_image_viewer/image_utils.py
abstract_image_viewer/pdf_module.py
abstract_image_viewer/pdf_utils.py
abstract_image_viewer/consoles/__init__.py
abstract_image_viewer/consoles/imageViewerTab/__init__.py
abstract_image_viewer/consoles/imageViewerTab/functions.py
abstract_image_viewer/consoles/imageViewerTab/imports.py
abstract_image_viewer/consoles/imageViewerTab/initFuncs.py
abstract_image_viewer/consoles/imageViewerTab/main.py
abstract_image_viewer/green_screen_delimiter/__init__.py
abstract_image_viewer/green_screen_delimiter/compare_screens.py
abstract_image_viewer/green_screen_delimiter/detect_allgreen.py
abstract_image_viewer/green_screen_delimiter/detect_green_screen_blur.py
abstract_image_viewer/green_screen_delimiter/get_new_imagepath.py
abstract_image_viewer-0.0.8.dist-info/METADATA
abstract_image_viewer-0.0.8.dist-info/WHEEL
abstract_image_viewer-0.0.8.dist-info/top_level.txt
abstract_image_viewer-0.0.8.dist-info/RECORD
