Metadata-Version: 2.4
Name: abstract_image_viewer
Version: 0.0.8
Summary: This module, part of the `abstract_essentials` package, provides utility functions for working with images and PDFs.
Home-page: https://github.com/AbstractEndeavors/abstract_image_viewer
Author: putkoff
Author-email: putkoff <partners@abstractendeavors.com>
Project-URL: Repository, https://github.com/AbstractEndeavors/abstract_image_viewer
Classifier: Development Status :: 3 - Alpha
Classifier: Intended Audience :: Developers
Classifier: License :: OSI Approved :: MIT License
Classifier: Programming Language :: Python :: 3
Classifier: Programming Language :: Python :: 3.11
Requires-Python: >=3.6
Requires-Dist: pyscreenshot
Requires-Dist: abstract_utilities
Requires-Dist: numpy
Requires-Dist: PyPDF2
Requires-Dist: pdf2image
Requires-Dist: abstract_gui
Requires-Dist: abstract_webtools
Requires-Dist: pytesseract
Requires-Dist: Pillow
Requires-Dist: scipy
Dynamic: author
Dynamic: home-page
Dynamic: requires-python
